{"splitPoints":[{"splitPointId":2728,"stageId":1316,"number":3,"distance":10.4},{"splitPointId":2729,"stageId":1316,"number":1,"distance":3.83},{"splitPointId":2731,"stageId":1316,"number":2,"distance":9.14}],"controls":[{"controlId":5574,"eventId":87,"stageId":1316,"type":"TimeControl","code":"TC19A","location":"Technical Zone IN","timingPrecision":"Minute","distance":62.65,"targetDuration":"01:02:00","targetDurationMs":3720000,"firstCarDueDateTime":"2019-08-25T11:20:00","firstCarDueDateTimeLocal":"2019-08-25T13:20:00+02:00","status":"Completed","controlPenalties":"All","roundingPolicy":"NoRounding","locked":true},{"controlId":5619,"eventId":87,"stageId":1316,"type":"TimeControl","code":"TC19","location":"Dhrontal","timingPrecision":"Minute","distance":24.45,"targetDuration":"00:30:00","targetDurationMs":1800000,"firstCarDueDateTime":"2019-08-25T10:15:00","firstCarDueDateTimeLocal":"2019-08-25T12:15:00+02:00","status":"Completed","controlPenalties":"All","roundingPolicy":"NoRounding","locked":true},{"controlId":5637,"eventId":87,"stageId":1316,"type":"FlyingFinish","code":"SF19","location":"Dhrontal 2","timingPrecision":"Thousandth","distance":null,"targetDuration":null,"targetDurationMs":null,"firstCarDueDateTime":null,"firstCarDueDateTimeLocal":null,"status":"Completed","controlPenalties":"None","roundingPolicy":"NoRounding","locked":true},{"controlId":5654,"eventId":87,"stageId":1316,"type":"StageStart","code":"SS19","location":"Dhrontal 2","timingPrecision":"Minute","distance":11.69,"targetDuration":"00:03:00","targetDurationMs":180000,"firstCarDueDateTime":"2019-08-25T10:18:00","firstCarDueDateTimeLocal":"2019-08-25T12:18:00+02:00","status":"Completed","controlPenalties":"None","roundingPolicy":"RoundToClosestMinute","locked":true}],"stageId":1316,"eventId":87,"number":19,"name":"Dhrontal 2","distance":11.69,"status":"Completed","stageType":"PowerStage","timingPrecision":"Thousandth","locked":true,"code":"SS19"}